uniswap/__init__.py
uniswap/assets/erc20.abi
uniswap/assets/erc20b32.abi
uniswap/assets/uniswap-v1/exchange.abi
uniswap/assets/uniswap-v1/factory.abi
uniswap/assets/uniswap-v2/factory.abi
uniswap/assets/uniswap-v2/router02.abi
uniswap/assets/uniswap-v3/factory.abi
uniswap/assets/uniswap-v3/multicall.abi
uniswap/assets/uniswap-v3/nonFungiblePositionManager.abi
uniswap/assets/uniswap-v3/pool.abi
uniswap/assets/uniswap-v3/quoter.abi
uniswap/assets/uniswap-v3/router.abi
uniswap/cli.py
uniswap/constants.py
uniswap/decorators.py
uniswap/exceptions.py
uniswap/py.typed
uniswap/token.py
uniswap/tokens.py
uniswap/types.py
uniswap/uniswap.py
uniswap/util.py
uniswap_python-0.6.2.dist-info/entry_points.txt
uniswap_python-0.6.2.dist-info/LICENSE
uniswap_python-0.6.2.dist-info/WHEEL
uniswap_python-0.6.2.dist-info/METADATA
uniswap_python-0.6.2.dist-info/RECORD
