Metadata-Version: 2.1
Name: uniswap-python
Version: 0.6.2
Summary: An unofficial Python wrapper for the decentralized exchange Uniswap
Home-page: https://github.com/shanefontaine/uniswap-python
License: MIT
Keywords: uniswap,ethereum,exchange,trading
Author: Shane Fontaine
Author-email: shane6fontaine@gmail.com
Requires-Python: >=3.7.2,<4.0.0
Classifier: Intended Audience :: Developers
Classifier: Intended Audience :: Financial and Insurance Industry
Classifier: Intended Audience :: Information Technology
Classifier: License :: OSI Approved :: MIT License
Classifier: Programming Language :: Python :: 3
Classifier: Programming Language :: Python :: 3.8
Classifier: Programming Language :: Python :: 3.9
Classifier: Programming Language :: Python :: 3.10
Classifier: Programming Language :: Python :: 3.11
Classifier: Topic :: Software Development :: Libraries :: Python Modules
Requires-Dist: click (>=8.0.3,<9.0.0)
Requires-Dist: python-dotenv
Requires-Dist: typing-extensions
Requires-Dist: web3 (>5.23.0,<7.0)
Project-URL: Repository, https://github.com/shanefontaine/uniswap-python
